ncache/__init__.py
ncache/ncache.py
ncache-0.3.dist-info/LICENSE
ncache-0.3.dist-info/METADATA
ncache-0.3.dist-info/WHEEL
ncache-0.3.dist-info/top_level.txt
ncache-0.3.dist-info/RECORD
