Metadata-Version: 2.1
Name: ncache
Version: 0.3
Summary: A simple and lightweight dictionary-based persistent cache for storing python objects.
Home-page: https://github.com/rsusik/ncache
Author: Robert Susik
Author-email: robert.susik@gmail.com
License: GPLv3
Platform: UNKNOWN
Classifier: Topic :: Utilities
Classifier: Intended Audience :: Developers
Classifier: Programming Language :: Python
Requires-Python: >=3.8
